phlab/__init__.py
phlab/experiment/__init__.py
phlab/model/__init__.py
phlab/model/kernel_dist_disp_osc.py
phlab/model/kernel_double_osc.py
phlab/model/kernel_single_osc.py
phlab/model/spec.py
phlab/visual/__init__.py
phlab-0.0.0.dev5.dist-info/LICENSE.md
phlab-0.0.0.dev5.dist-info/METADATA
phlab-0.0.0.dev5.dist-info/WHEEL
phlab-0.0.0.dev5.dist-info/top_level.txt
phlab-0.0.0.dev5.dist-info/RECORD
