Metadata-Version: 2.1
Name: phlab
Version: 0.0.0.dev5
Summary: Phonon contirbution in RIXS
Home-page: https://github.com/geonda/RIXS.phonons/
License: UNKNOWN
Platform: UNKNOWN
Requires-Python: >=3.6
Requires-Dist: lmfit (==1.0.1)
Requires-Dist: matplotlib (==3.2.1)
Requires-Dist: numpy (==1.18.4)
Requires-Dist: pathos (==0.2.5)
Requires-Dist: scipy (==1.4.1)
Requires-Dist: tqdm (==4.46.0)
